scGCO/GMM.py
scGCO/Graph_cut.py
scGCO/Preprocessing.py
scGCO/Visualization.py
scGCO/__init__.py
scGCO-1.1.3.dist-info/AUTHORS
scGCO-1.1.3.dist-info/LICENSE
scGCO-1.1.3.dist-info/METADATA
scGCO-1.1.3.dist-info/WHEEL
scGCO-1.1.3.dist-info/top_level.txt
scGCO-1.1.3.dist-info/RECORD
